setup.py
django_dynamic_finder/__init__.py
django_dynamic_finder/managers.py
django_dynamic_finder.egg-info/PKG-INFO
django_dynamic_finder.egg-info/SOURCES.txt
django_dynamic_finder.egg-info/dependency_links.txt
django_dynamic_finder.egg-info/requires.txt
django_dynamic_finder.egg-info/top_level.txt