Metadata-Version: 1.1
Name: django-dynamic-finder
Version: 0.1
Summary: A Django version of the Rails Dynamic Finder, using Django Managers.
Home-page: https://github.com/luanfonceca/django-dynamic-finder
Author: Luan Fonseca
Author-email: luanfonceca@gmail.com
License: BSD
Platform: UNKNOWN
Classifier: Development Status :: 3 - Alpha
Classifier: Environment :: Web Environment
Classifier: Framework :: Django
Classifier: Intended Audience :: Developers
Classifier: License :: OSI Approved :: MIT License
Classifier: Natural Language :: English
Classifier: Operating System :: OS Independent
Classifier: Programming Language :: Python
